LICENSE.txt
README.md
setup.cfg
setup.py
socket_like_requests/__init__.py
socket_like_requests/slr.py
socket_like_requests.egg-info/PKG-INFO
socket_like_requests.egg-info/SOURCES.txt
socket_like_requests.egg-info/dependency_links.txt
socket_like_requests.egg-info/top_level.txt