Metadata-Version: 2.1
Name: socket-like-requests
Version: 0.0.12
Summary: Use Socket Like Requests Module
Home-page: https://github.com/zvhh/Socket-Like-Requests
Download-URL: https://github.com/zvhh/Socket-Like-Requests/archive/refs/tags/0.0.12.tar.gz
Author: Sami
Author-email: sami2700@outlook.com
License: MIT
Keywords: Requests,TCP Request,Socket
Classifier: Development Status :: 3 - Alpha
Classifier: Intended Audience :: Developers
Classifier: Topic :: Software Development :: Build Tools
Classifier: License :: OSI Approved :: MIT License
Classifier: Programming Language :: Python :: 3.11
License-File: LICENSE.txt
